.gitignore
.readthedocs.yml
.travis.yml
CHANGELOG.rst
LICENSE
MANIFEST.in
README.rst
setup.cfg
setup.py
tox.ini
docs/Makefile
docs/conf.py
docs/index.rst
docs/installation.rst
docs/_static/custom.css
docs/_static/favicon.ico
docs/_static/logo.png
docs/_static/logo_packed.png
docs/_templates/about.html
docs/api/index.rst
docs/usage/standalone.rst
docs/usage/tendril.rst
src/tendril/__init__.py
src/tendril/artefacts/__init__.py
src/tendril/artefacts/base.py
src/tendril/artefacts/db/__init__.py
src/tendril/artefacts/db/controller.py
src/tendril/artefacts/db/model.py
src/tendril/authz/__init__.py
src/tendril/authz/roles/__init__.py
src/tendril/authz/roles/artefacts.py
src/tendril_artefacts.egg-info/PKG-INFO
src/tendril_artefacts.egg-info/SOURCES.txt
src/tendril_artefacts.egg-info/dependency_links.txt
src/tendril_artefacts.egg-info/requires.txt
src/tendril_artefacts.egg-info/top_level.txt
tests/__init__.py
tests/coveralls.py